Codes/fc_layer.v
module fc_layer(input clk, input rst, input [7:0] data_in, output reg [7:0] data_out);
    reg [7:0] weight = 8'd3;
    always @(posedge clk or posedge rst) begin
        if (rst)
            data_out <= 0;
        else
            data_out <= data_in * weight;
    end
endmodule

Codes/pool_layer.v
module pool_layer(input clk, input rst, input [7:0] data_in, output reg [7:0] data_out);
    // Simple down-sampling: output every 2nd value
    reg toggle;
    always @(posedge clk or posedge rst) begin
        if (rst) begin
            data_out <= 0;
            toggle <= 0;
        end else begin
            toggle <= ~toggle;
            if (toggle)
                data_out <= data_in;
        end
    end
endmodule

Codes/relu_layer.v
module relu_layer(input signed [7:0] data_in, output [7:0] data_out);
    assign data_out = (data_in[7] == 1) ? 8'd0 : data_in;  // clamp negatives
endmodule

Codes/conv_layer.v
module conv_layer(input clk, input rst, input [7:0] pixel_in, output reg [7:0] pixel_out);
    reg [7:0] kernel = 8'd2;  // fixed weight for simplicity

    always @(posedge clk or posedge rst) begin
        if (rst)
            pixel_out <= 0;
        else
            pixel_out <= pixel_in * kernel;
    end
endmodule

Codes/cnn_top.v
module cnn_top(input clk, input rst, input [7:0] pixel_in, output [7:0] result);

    wire [7:0] conv_out;
    wire [7:0] relu_out;
    wire [7:0] pool_out;
    wire [7:0] fc_out;

    conv_layer u1 (.clk(clk), .rst(rst), .pixel_in(pixel_in), .pixel_out(conv_out));
    relu_layer u2 (.data_in(conv_out), .data_out(relu_out));
    pool_layer u3 (.clk(clk), .rst(rst), .data_in(relu_out), .data_out(pool_out));
    fc_layer   u4 (.clk(clk), .rst(rst), .data_in(pool_out), .data_out(fc_out));

    assign result = fc_out;
endmodule

Codes/testbench.v
`timescale 1ns/1ps

module testbench;
    reg clk, rst;
    reg [7:0] pixel_in;
    wire [7:0] result;

    cnn_top DUT(.clk(clk), .rst(rst), .pixel_in(pixel_in), .result(result));

    always #5 clk = ~clk;

    initial begin
        $dumpfile("cnn.vcd");
        $dumpvars(0, testbench);

        clk = 0; rst = 1; pixel_in = 0;
        #10 rst = 0;

        pixel_in = 8'd5; #10;
        pixel_in = 8'd7; #10;
        pixel_in = 8'd10; #10;

        #50 $finish;
    end
endmodule

Codes/cnn.vcd
$date
	Sun Sep 14 08:15:58 2025
$end
$version
	Icarus Verilog
$end
$timescale
	1ps
$end
$scope module testbench $end
$var wire 8 ! result [7:0] $end
$var reg 1 " clk $end
$var reg 8 # pixel_in [7:0] $end
$var reg 1 $ rst $end
$scope module DUT $end
$var wire 1 " clk $end
$var wire 8 % pixel_in [7:0] $end
$var wire 8 & result [7:0] $end
$var wire 1 $ rst $end
$var wire 8 ' relu_out [7:0] $end
$var wire 8 ( pool_out [7:0] $end
$var wire 8 ) fc_out [7:0] $end
$var wire 8 * conv_out [7:0] $end
$scope module u1 $end
$var wire 1 " clk $end
$var wire 8 + pixel_in [7:0] $end
$var wire 1 $ rst $end
$var reg 8 , kernel [7:0] $end
$var reg 8 - pixel_out [7:0] $end
$upscope $end
$scope module u2 $end
$var wire 8 . data_in [7:0] $end
$var wire 8 / data_out [7:0] $end
$upscope $end
$scope module u3 $end
$var wire 1 " clk $end
$var wire 8 0 data_in [7:0] $end
$var wire 1 $ rst $end
$var reg 8 1 data_out [7:0] $end
$var reg 1 2 toggle $end
$upscope $end
$scope module u4 $end
$var wire 1 " clk $end
$var wire 8 3 data_in [7:0] $end
$var wire 1 $ rst $end
$var reg 8 4 data_out [7:0] $end
$var reg 8 5 weight [7:0] $end
$upscope $end
$upscope $end
$upscope $end
$enddefinitions $end
$comment Show the parameter values. $end
$dumpall
$end
#0
$dumpvars
b11 5
b0 4
b0 3
02
b0 1
b0 0
b0 /
b0 .
b0 -
b10 ,
b0 +
b0 *
b0 )
b0 (
b0 '
b0 &
b0 %
1$
b0 #
0"
b0 !
$end
#5000
1"
#10000
0"
b101 #
b101 %
b101 +
0$
#15000
b1010 '
b1010 /
b1010 0
b1010 *
b1010 -
b1010 .
12
1"
#20000
0"
b111 #
b111 %
b111 +
#25000
b1110 '
b1110 /
b1110 0
b1010 (
b1010 1
b1010 3
02
b1110 *
b1110 -
b1110 .
1"
#30000
0"
b1010 #
b1010 %
b1010 +
#35000
b10100 '
b10100 /
b10100 0
b10100 *
b10100 -
b10100 .
12
b11110 !
b11110 &
b11110 )
b11110 4
1"
#40000
0"
#45000
b10100 (
b10100 1
b10100 3
02
1"
#50000
0"
#55000
12
b111100 !
b111100 &
b111100 )
b111100 4
1"
#60000
0"
#65000
02
1"
#70000
0"
#75000
12
1"
#80000
0"
#85000
02
1"
